libertem_holo/__init__.py
libertem_holo/__version__.py
libertem_holo/versioning.py
libertem_holo/base/__init__.py
libertem_holo/base/align.py
libertem_holo/base/filters.py
libertem_holo/base/generate.py
libertem_holo/base/mask.py
libertem_holo/base/reconstr.py
libertem_holo/base/utils.py
libertem_holo/udf/__init__.py
libertem_holo/udf/reconstr.py
libertem_holo-0.1.0.dist-info/METADATA
libertem_holo-0.1.0.dist-info/WHEEL
libertem_holo-0.1.0.dist-info/licenses/LICENSE
libertem_holo-0.1.0.dist-info/RECORD
