Metadata-Version: 2.4
Name: libertem-holo
Version: 0.1.0
Summary: Electron holography reconstruction using LiberTEM
Project-URL: Repository, https://github.com/LiberTEM/LiberTEM-holo
Project-URL: Documentation, https://libertem.github.io/LiberTEM-holo
Author-email: Alexander Clausen <a.clausen@fz-juelich.de>, Dieter Weber <d.weber@fz-juelich.de>, Patrick Adrian <patrick.adrian.gunawan@stud.th-luebeck.de>
License-File: LICENSE
Keywords: electron microscopy,holography,off-axis holography
Classifier: Development Status :: 4 - Beta
Classifier: Environment :: Console
Classifier: Intended Audience :: Developers
Classifier: Intended Audience :: End Users/Desktop
Classifier: Intended Audience :: Science/Research
Classifier: License :: OSI Approved :: GNU General Public License v3 (GPLv3)
Classifier: Natural Language :: English
Classifier: Operating System :: MacOS :: MacOS X
Classifier: Operating System :: Microsoft :: Windows
Classifier: Operating System :: POSIX :: Linux
Classifier: Programming Language :: Python :: 3.9
Classifier: Programming Language :: Python :: 3.10
Classifier: Programming Language :: Python :: 3.11
Classifier: Programming Language :: Python :: 3.12
Classifier: Topic :: Scientific/Engineering
Classifier: Topic :: Scientific/Engineering :: Physics
Classifier: Topic :: Scientific/Engineering :: Visualization
Requires-Python: >=3.9
Requires-Dist: empyre
Requires-Dist: libertem
Requires-Dist: numba>=0.53; python_version < '3.10'
Requires-Dist: numba>=0.55; python_version < '3.11'
Requires-Dist: numba>=0.57; python_version < '3.12'
Requires-Dist: numba>=0.59; python_version < '3.13'
Requires-Dist: numba>=0.61; python_version < '3.14' and python_version >= '3.10'
Requires-Dist: numba>=0.61; python_version >= '3.14'
Requires-Dist: numpy
Requires-Dist: scikit-image
Requires-Dist: scipy
Requires-Dist: sparse
Requires-Dist: sparseconverter
